<?xml version="1.0"?>
<MEDMLDATA xmlns="PhaseForward-MedML-Inform4">


<RIGHTSGROUP  GROUPNAME="Coding Query Rights Group">
<!-- Insert Users -->
<USERREF USERNAME="coder_query"/>

</RIGHTSGROUP>

<RIGHTSGROUP  GROUPNAME="Data Manager">
<!-- Insert Users -->
<USERREF USERNAME="z3x2633"/>
<USERREF USERNAME="z1x5585"/>
<USERREF USERNAME="z1x9560"/>
<USERREF USERNAME="c184994"/>
<USERREF USERNAME="z1x3734"/>
<USERREF USERNAME="z1x9186"/>
<USERREF USERNAME="z1x6008"/>
<USERREF USERNAME="z1x3917"/>

</RIGHTSGROUP>

<RIGHTSGROUP  GROUPNAME="Developer">
<!-- Insert Users -->
<USERREF USERNAME="c184178"/>
<USERREF USERNAME="c201052"/>
<USERREF USERNAME="c174838"/>
<USERREF USERNAME="z1x4636"/>

</RIGHTSGROUP>

<RIGHTSGROUP  GROUPNAME="GPS">
<!-- Insert Users -->
<USERREF USERNAME="c206591"/>
<USERREF USERNAME="c039853"/>
<USERREF USERNAME="ye91098"/>
<USERREF USERNAME="yex7972"/>
<USERREF USERNAME="c025980"/>
<USERREF USERNAME="c060736"/>
<USERREF USERNAME="a608261"/>
<USERREF USERNAME="c003859"/>
<USERREF USERNAME="c149066"/>
<USERREF USERNAME="rm35504"/>
<USERREF USERNAME="v6x8356"/>
<USERREF USERNAME="c039863"/>
<USERREF USERNAME="c149176"/>
<USERREF USERNAME="c075541"/>
<USERREF USERNAME="c074429"/>
<USERREF USERNAME="c026393"/>
<USERREF USERNAME="c026390"/>
<USERREF USERNAME="a608760"/>
<USERREF USERNAME="c058698"/>
<USERREF USERNAME="u7x2510"/>
<USERREF USERNAME="c149470"/>
<USERREF USERNAME="a803075"/>
<USERREF USERNAME="rm87794"/>
<USERREF USERNAME="c196248"/>
<USERREF USERNAME="c218621"/>
<USERREF USERNAME="c196683"/>
<USERREF USERNAME="c228249"/>
<USERREF USERNAME="c228246"/>
<USERREF USERNAME="c228247"/>
<USERREF USERNAME="c228248"/>
<USERREF USERNAME="c228250"/>
<USERREF USERNAME="c143125"/>
<USERREF USERNAME="c135748"/>
<USERREF USERNAME="rm36132"/>
<USERREF USERNAME="a511471"/>
<USERREF USERNAME="rm80655"/>
<USERREF USERNAME="c199642"/>
<USERREF USERNAME="c223292"/>
<USERREF USERNAME="c068502"/>
<USERREF USERNAME="c083101"/>
<USERREF USERNAME="c219905"/>
<USERREF USERNAME="c069132"/>
<USERREF USERNAME="c071673"/>
<USERREF USERNAME="v6x8058"/>
<USERREF USERNAME="c074090"/>
<USERREF USERNAME="c090108"/>
<USERREF USERNAME="c022433"/>
<USERREF USERNAME="yex7920"/>
<USERREF USERNAME="c079244"/>
<USERREF USERNAME="rm90029"/>
<USERREF USERNAME="c057362"/>
<USERREF USERNAME="c039825"/>
<USERREF USERNAME="c068505"/>
<USERREF USERNAME="c085302"/>
<USERREF USERNAME="c074342"/>
<USERREF USERNAME="c131994"/>
<USERREF USERNAME="c137396"/>
<USERREF USERNAME="c219898"/>
<USERREF USERNAME="a701824"/>
<USERREF USERNAME="c015393"/>
<USERREF USERNAME="c021984"/>
<USERREF USERNAME="rm89018"/>
<USERREF USERNAME="c149177"/>

</RIGHTSGROUP>

<RIGHTSGROUP  GROUPNAME="ODM Rights Group">
<!-- Insert Users -->
<USERREF USERNAME="odm_user"/>

</RIGHTSGROUP>

<RIGHTSGROUP  GROUPNAME="PFView Only">
<!-- Insert Users -->
<USERREF USERNAME="ZPFaflathers"/>
<USERREF USERNAME="ZPFkbarkoczi"/>
<USERREF USERNAME="ZPFskonig"/>

</RIGHTSGROUP>

<RIGHTSGROUP  GROUPNAME="PI">
<!-- Insert Users -->
<USERREF USERNAME="rgeorge"/>
<USERREF USERNAME="mbertolo"/>

</RIGHTSGROUP>

<RIGHTSGROUP  GROUPNAME="PI Sign Only">
<!-- Insert Users -->
<USERREF USERNAME="igarciadelatorre"/>
<USERREF USERNAME="abinda"/>
<USERREF USERNAME="aabinader"/>
<USERREF USERNAME="gburmester"/>
<USERREF USERNAME="psarziputtini"/>
<USERREF USERNAME="gmedranorimirez"/>
<USERREF USERNAME="ebottcher"/>
<USERREF USERNAME="psunkureddi"/>
<USERREF USERNAME="dmehta"/>
<USERREF USERNAME="mtrevino"/>
<USERREF USERNAME="akivitz"/>
<USERREF USERNAME="jmirandalimon"/>
<USERREF USERNAME="bzazuetamontiel"/>

</RIGHTSGROUP>

<RIGHTSGROUP  GROUPNAME="Report Extractor">
<!-- Insert Users -->
<USERREF USERNAME="i8kmcjpda_RE"/>

</RIGHTSGROUP>

<RIGHTSGROUP  GROUPNAME="SC">
<!-- Insert Users -->
<USERREF USERNAME="everduzcomora"/>
<USERREF USERNAME="mwalker"/>
<USERREF USERNAME="ialdana"/>
<USERREF USERNAME="emunozesteves"/>
<USERREF USERNAME="aramirez"/>
<USERREF USERNAME="mzauner"/>
<USERREF USERNAME="ahagemann"/>
<USERREF USERNAME="btrezzi"/>
<USERREF USERNAME="mzumer"/>
<USERREF USERNAME="klaughon"/>
<USERREF USERNAME="wrubach"/>
<USERREF USERNAME="svollenklee"/>
<USERREF USERNAME="ozamani"/>
<USERREF USERNAME="rsuarezotero"/>
<USERREF USERNAME="aurendaquezada"/>
<USERREF USERNAME="dvaldes"/>
<USERREF USERNAME="azazuetamontiel"/>
<USERREF USERNAME="igarciavallardes"/>
<USERREF USERNAME="svargas"/>
<USERREF USERNAME="brydecka"/>
<USERREF USERNAME="mbenard"/>
<USERREF USERNAME="aklatt"/>
<USERREF USERNAME="jgruber"/>
<USERREF USERNAME="hradner"/>
<USERREF USERNAME="lhoskins"/>
<USERREF USERNAME="dkivanova"/>

</RIGHTSGROUP>

<RIGHTSGROUP  GROUPNAME="User Activator RG">
<!-- Insert Users -->
<USERREF USERNAME="ZPFprojas"/>
<USERREF USERNAME="ZPFobodnar"/>
<USERREF USERNAME="ZPFnkovacs"/>
<USERREF USERNAME="ZPFmandone"/>
<USERREF USERNAME="ZPFepenzes"/>
<USERREF USERNAME="ZPFrcalorico"/>
<USERREF USERNAME="ZPFdnagy"/>
<USERREF USERNAME="ZPFckalinyak"/>
<USERREF USERNAME="ZPFabalogh"/>
<USERREF USERNAME="ZPFsdamato"/>
<USERREF USERNAME="ZPFrducusin"/>
<USERREF USERNAME="ZPFedervishaj"/>

</RIGHTSGROUP>

<RIGHTSGROUP  GROUPNAME="User Manager RG">
<!-- Insert Users -->
<USERREF USERNAME="ZPFijohl"/>
<USERREF USERNAME="ZPFkcco"/>
<USERREF USERNAME="ZPFkcsobalyka"/>
<USERREF USERNAME="ZPFkkovacs"/>
<USERREF USERNAME="ZPFklim"/>
<USERREF USERNAME="ZPFlbalubar"/>
<USERREF USERNAME="ZPFlmate"/>
<USERREF USERNAME="ZPFmkhella"/>
<USERREF USERNAME="ZPFmtoth"/>
<USERREF USERNAME="ZPFnqi"/>
<USERREF USERNAME="ZPFnreis"/>
<USERREF USERNAME="ZPFnvergara"/>
<USERREF USERNAME="ZPFoely"/>
<USERREF USERNAME="ZPFpvallar"/>
<USERREF USERNAME="ZPFrsulit"/>
<USERREF USERNAME="ZPFsaguilar"/>
<USERREF USERNAME="ZPFsdasilva"/>
<USERREF USERNAME="ZPFskholti"/>
<USERREF USERNAME="ZPFstayco"/>
<USERREF USERNAME="ZPFtcabanes"/>
<USERREF USERNAME="ZPFtfabian"/>
<USERREF USERNAME="ZPFgyvarga"/>
<USERREF USERNAME="ZPFtszabo"/>
<USERREF USERNAME="ZPFfvarga"/>
<USERREF USERNAME="ZPFfillesy"/>
<USERREF USERNAME="ZPFekosa"/>
<USERREF USERNAME="ZPFdvittay"/>
<USERREF USERNAME="ZPFddiomede"/>
<USERREF USERNAME="ZPFcmolom"/>
<USERREF USERNAME="ZPFcmercado"/>
<USERREF USERNAME="ZPFawarsama"/>
<USERREF USERNAME="ZPFaterjek"/>
<USERREF USERNAME="ZPFapervaiz"/>
<USERREF USERNAME="ZPFgkrucso"/>

</RIGHTSGROUP>

<RIGHTSGROUP  GROUPNAME="VO">
<!-- Insert Users -->
<USERREF USERNAME="c199540"/>
<USERREF USERNAME="c224051"/>
<USERREF USERNAME="rm37067"/>
<USERREF USERNAME="c217655"/>
<USERREF USERNAME="z2x7596"/>
<USERREF USERNAME="c195674"/>
<USERREF USERNAME="c188384"/>
<USERREF USERNAME="c201427"/>
<USERREF USERNAME="v2x5112"/>
<USERREF USERNAME="c219791"/>
<USERREF USERNAME="c211658"/>
<USERREF USERNAME="c207830"/>
<USERREF USERNAME="u8x6878"/>
<USERREF USERNAME="c211710"/>
<USERREF USERNAME="c213671"/>
<USERREF USERNAME="c218936"/>
<USERREF USERNAME="c205056"/>
<USERREF USERNAME="c217683"/>
<USERREF USERNAME="c203439"/>

</RIGHTSGROUP>

</MEDMLDATA>